deepdelta/__init__.py
deepdelta/comparator.py
deepdelta/core.py
deepdelta/delta_config.py
deepdelta/delta_output.py
deepdelta-1.0.1.dist-info/LICENSE
deepdelta-1.0.1.dist-info/METADATA
deepdelta-1.0.1.dist-info/WHEEL
deepdelta-1.0.1.dist-info/top_level.txt
deepdelta-1.0.1.dist-info/RECORD
