Metadata-Version: 2.1
Name: deepdelta
Version: 1.0.1
Summary: Python comparator with rich options, configurable named or typed comparators to get deep differences of any two objects.
Home-page: https://github.com/Cruisoring/DeepDelta
Author: William JIANG
Author-email: williamjiang0218@gmail.com
License: MIT
Platform: UNKNOWN
Classifier: License :: OSI Approved :: MIT License
Classifier: Programming Language :: Python
Classifier: Programming Language :: Python :: 3
